tests/__init__.py
tests/test_tqdmp.py
tqdmp/__init__.py
tqdmp/tqdmp.py
tqdmp-0.0.3.dist-info/LICENSE
tqdmp-0.0.3.dist-info/METADATA
tqdmp-0.0.3.dist-info/WHEEL
tqdmp-0.0.3.dist-info/top_level.txt
tqdmp-0.0.3.dist-info/RECORD
